eintorch/.DS_Store
eintorch/__init__.py
eintorch/_core.py
eintorch/_functions.py
eintorch/_preprocessing.py
eintorch/_utils.py
eintorch-0.2.5.dist-info/LICENSE
eintorch-0.2.5.dist-info/METADATA
eintorch-0.2.5.dist-info/WHEEL
eintorch-0.2.5.dist-info/RECORD
