Metadata-Version: 2.1
Name: eintorch
Version: 0.2.5
Summary: An alternative interface for torchdim
Author: Jakub Bachurski
Author-email: kbachurski@gmail.com
Requires-Python: >=3.8,<4.0
Classifier: Programming Language :: Python :: 3
Classifier: Programming Language :: Python :: 3.8
Classifier: Programming Language :: Python :: 3.9
Classifier: Programming Language :: Python :: 3.10
Classifier: Programming Language :: Python :: 3.11
